[
  {
    "ruta_foto": "/media/warcklian/DATA_500GB/CODE/SISTEMA_PASAPORTES_FINAL/DATA/Imagenes_Mujeres/massive_venezuelan_mujer_37_1003_20251002_184415.png",
    "numero_pasaporte_1": "121624044",
    "numero_pasaporte_2": "121624044",
    "numero_pasaporte": "121624044",
    "tipo": "P",
    "pais_emisor": "VEN",
    "nombre_completo": "AINTZA",
    "apellido_completo": "GARCIA SERRANO",
    "fecha_nacimiento": "14/Ene/Ene/1988",
    "cedula": "47198356",
    "fecha_emision": "12/May/May/2025",
    "fecha_vencimiento": "12/Ene/Ene/2035",
    "sexo": "F",
    "nacionalidad": "VENEZOLANA",
    "lugar_nacimiento": "CARACAS VEN",
    "codigo_verificacion": "14-01-88",
    "firma": "A. Garcia Serrano",
    "fuente_firma": "White Sign (DemoVersion).otf",
    "mrz_linea1": "P<VENGARCIASERRANO<<<<<<<<<AINTZA<<<<<<<<<<<",
    "mrz_linea2": "1216240445VEN880114F9801012<<<<<<<<<<<<<<<6<",
    "edad": 37,
    "correo_original": "a1ntz4_g4rc14_14@hotmail.com",
    "imagen_usada": "/media/warcklian/DATA_500GB/CODE/SISTEMA_PASAPORTES_FINAL/DATA/Imagenes_Mujeres/massive_venezuelan_mujer_37_1003_20251002_184415.png",
    "nombre_archivo": "a1ntz4_g4rc14_14@hotmail.com.png",
    "pasaporte_visual": "/media/warcklian/DATA_500GB/CODE/SISTEMA_PASAPORTES_FINAL/OUTPUT/pasaportes_visuales/a1ntz4_g4rc14_14@hotmail.com.png",
    "estado": "generado"
  },
  {
    "ruta_foto": "/media/warcklian/DATA_500GB/CODE/SISTEMA_PASAPORTES_FINAL/DATA/Imagenes_Mujeres/massive_venezuelan_mujer_48_2353_20251002_103828.png",
    "numero_pasaporte_1": "139865299",
    "numero_pasaporte_2": "139865299",
    "numero_pasaporte": "139865299",
    "tipo": "P",
    "pais_emisor": "VEN",
    "nombre_completo": "ALICIA",
    "apellido_completo": "JIMENEZ GALLEGO",
    "fecha_nacimiento": "04/May/May/1970",
    "cedula": "81922591",
    "fecha_emision": "20/Jun/Jun/2025",
    "fecha_vencimiento": "20/Ene/Ene/2035",
    "sexo": "F",
    "nacionalidad": "VENEZOLANA",
    "lugar_nacimiento": "MARACAIBO VEN",
    "codigo_verificacion": "04-05-70",
    "firma": "Ali-Jim",
    "fuente_firma": "White Sign (DemoVersion).otf",
    "mrz_linea1": "P<VENJIMENEZGALLEGO<<<<<<<<ALICIA<<<<<<<<<<<",
    "mrz_linea2": "1398652994VEN700504F8001017<<<<<<<<<<<<<<<9<",
    "edad": 55,
    "correo_original": "al1c14_j1m3n3z_04@outlook.com",
    "imagen_usada": "/media/warcklian/DATA_500GB/CODE/SISTEMA_PASAPORTES_FINAL/DATA/Imagenes_Mujeres/massive_venezuelan_mujer_48_2353_20251002_103828.png",
    "nombre_archivo": "al1c14_j1m3n3z_04@outlook.com.png",
    "pasaporte_visual": "/media/warcklian/DATA_500GB/CODE/SISTEMA_PASAPORTES_FINAL/OUTPUT/pasaportes_visuales/al1c14_j1m3n3z_04@outlook.com.png",
    "estado": "generado"
  },
  {
    "ruta_foto": "/media/warcklian/DATA_500GB/CODE/SISTEMA_PASAPORTES_FINAL/DATA/Imagenes_Mujeres/massive_venezuelan_mujer_26_3253_20251002_103828.png",
    "numero_pasaporte_1": "161671076",
    "numero_pasaporte_2": "161671076",
    "numero_pasaporte": "161671076",
    "tipo": "P",
    "pais_emisor": "VEN",
    "nombre_completo": "BIANCCIA",
    "apellido_completo": "IBANEZ KORSEN",
    "fecha_nacimiento": "21/Jul/Jul/1999",
    "cedula": "50914157",
    "fecha_emision": "26/Dic/Dic/2024",
    "fecha_vencimiento": "26/Ene/Ene/2034",
    "sexo": "F",
    "nacionalidad": "VENEZOLANA",
    "lugar_nacimiento": "BARCELONA VEN",
    "codigo_verificacion": "21-07-99",
    "firma": "Bia Ib",
    "fuente_firma": "White Sign (DemoVersion).otf",
    "mrz_linea1": "P<VENIBANEZKORSEN<<<<<<<<<<BIANCCIA<<<<<<<<<",
    "mrz_linea2": "1616710764VEN990721F0901018<<<<<<<<<<<<<<<1<",
    "edad": 26,
    "correo_original": "b14ncc14_1b4n3z_21@hotmail.com",
    "imagen_usada": "/media/warcklian/DATA_500GB/CODE/SISTEMA_PASAPORTES_FINAL/DATA/Imagenes_Mujeres/massive_venezuelan_mujer_26_3253_20251002_103828.png",
    "nombre_archivo": "b14ncc14_1b4n3z_21@hotmail.com.png",
    "pasaporte_visual": "/media/warcklian/DATA_500GB/CODE/SISTEMA_PASAPORTES_FINAL/OUTPUT/pasaportes_visuales/b14ncc14_1b4n3z_21@hotmail.com.png",
    "estado": "generado"
  },
  {
    "ruta_foto": "/media/warcklian/DATA_500GB/CODE/SISTEMA_PASAPORTES_FINAL/DATA/Imagenes_Mujeres/massive_venezuelan_mujer_18_1664_20251002_103828.png",
    "numero_pasaporte_1": "181028574",
    "numero_pasaporte_2": "181028574",
    "numero_pasaporte": "181028574",
    "tipo": "P",
    "pais_emisor": "VEN",
    "nombre_completo": "ROSIBEL",
    "apellido_completo": "GARCILOPE MOLINA",
    "fecha_nacimiento": "24/Mar/Mar/1966",
    "cedula": "25495949",
    "fecha_emision": "13/Mar/Mar/2024",
    "fecha_vencimiento": "13/Ene/Ene/2034",
    "sexo": "F",
    "nacionalidad": "VENEZOLANA",
    "lugar_nacimiento": "LA GUAIRA VEN",
    "codigo_verificacion": "24-03-66",
    "firma": "Garc R",
    "fuente_firma": "White Sign (DemoVersion).otf",
    "mrz_linea1": "P<VENGARCILOPEMOLINA<<<<<<<ROSIBEL<<<<<<<<<<",
    "mrz_linea2": "1810285745VEN660324F7601018<<<<<<<<<<<<<<<7<",
    "edad": 59,
    "correo_original": "r051b3l_g4rc1l0p3_24@outlook.com",
    "imagen_usada": "/media/warcklian/DATA_500GB/CODE/SISTEMA_PASAPORTES_FINAL/DATA/Imagenes_Mujeres/massive_venezuelan_mujer_18_1664_20251002_103828.png",
    "nombre_archivo": "r051b3l_g4rc1l0p3_24@outlook.com.png",
    "pasaporte_visual": "/media/warcklian/DATA_500GB/CODE/SISTEMA_PASAPORTES_FINAL/OUTPUT/pasaportes_visuales/r051b3l_g4rc1l0p3_24@outlook.com.png",
    "estado": "generado"
  },
  {
    "ruta_foto": "/media/warcklian/DATA_500GB/CODE/SISTEMA_PASAPORTES_FINAL/DATA/Imagenes_Mujeres/massive_venezuelan_mujer_26_1669_20251002_103828.png",
    "numero_pasaporte_1": "177366668",
    "numero_pasaporte_2": "177366668",
    "numero_pasaporte": "177366668",
    "tipo": "P",
    "pais_emisor": "VEN",
    "nombre_completo": "BRENDA",
    "apellido_completo": "ARMIDA DELGADO",
    "fecha_nacimiento": "18/Dic/Dic/1998",
    "cedula": "40422551",
    "fecha_emision": "15/Jun/Jun/2021",
    "fecha_vencimiento": "15/Ene/Ene/2031",
    "sexo": "F",
    "nacionalidad": "VENEZOLANA",
    "lugar_nacimiento": "BARINAS VEN",
    "codigo_verificacion": "18-12-98",
    "firma": "A. Bren",
    "fuente_firma": "White Sign (DemoVersion).otf",
    "mrz_linea1": "P<VENARMIDADELGADO<<<<<<<<<BRENDA<<<<<<<<<<<",
    "mrz_linea2": "1773666686VEN981218F0801017<<<<<<<<<<<<<<<8<",
    "edad": 26,
    "correo_original": "br3nd4_4rm1d4_18@hotmail.com",
    "imagen_usada": "/media/warcklian/DATA_500GB/CODE/SISTEMA_PASAPORTES_FINAL/DATA/Imagenes_Mujeres/massive_venezuelan_mujer_26_1669_20251002_103828.png",
    "nombre_archivo": "br3nd4_4rm1d4_18@hotmail.com.png",
    "pasaporte_visual": "/media/warcklian/DATA_500GB/CODE/SISTEMA_PASAPORTES_FINAL/OUTPUT/pasaportes_visuales/br3nd4_4rm1d4_18@hotmail.com.png",
    "estado": "generado"
  },
  {
    "ruta_foto": "/media/warcklian/DATA_500GB/CODE/SISTEMA_PASAPORTES_FINAL/DATA/Imagenes_Mujeres/massive_venezuelan_mujer_28_738_20250930_104411.png",
    "numero_pasaporte_1": "103457735",
    "numero_pasaporte_2": "103457735",
    "numero_pasaporte": "103457735",
    "tipo": "P",
    "pais_emisor": "VEN",
    "nombre_completo": "CELIA",
    "apellido_completo": "AMANDA CASTRO",
    "fecha_nacimiento": "13/Feb/Feb/1997",
    "cedula": "40718348",
    "fecha_emision": "26/Dic/Dic/2022",
    "fecha_vencimiento": "26/Ene/Ene/2032",
    "sexo": "F",
    "nacionalidad": "VENEZOLANA",
    "lugar_nacimiento": "PUERTO AYACUCHO VEN",
    "codigo_verificacion": "13-02-97",
    "firma": "C. Aman",
    "fuente_firma": "White Sign (DemoVersion).otf",
    "mrz_linea1": "P<VENAMANDACASTRO<<<<<<<<<<CELIA<<<<<<<<<<<<",
    "mrz_linea2": "1034577356VEN970213F0701019<<<<<<<<<<<<<<<6<",
    "edad": 28,
    "correo_original": "c3l14_4m4nd4_13@hotmail.com",
    "imagen_usada": "/media/warcklian/DATA_500GB/CODE/SISTEMA_PASAPORTES_FINAL/DATA/Imagenes_Mujeres/massive_venezuelan_mujer_28_738_20250930_104411.png",
    "nombre_archivo": "c3l14_4m4nd4_13@hotmail.com.png",
    "pasaporte_visual": "/media/warcklian/DATA_500GB/CODE/SISTEMA_PASAPORTES_FINAL/OUTPUT/pasaportes_visuales/c3l14_4m4nd4_13@hotmail.com.png",
    "estado": "generado"
  },
  {
    "ruta_foto": "/media/warcklian/DATA_500GB/CODE/SISTEMA_PASAPORTES_FINAL/DATA/Imagenes_Mujeres/massive_venezuelan_mujer_40_3167_20251002_103828.png",
    "numero_pasaporte_1": "103647370",
    "numero_pasaporte_2": "103647370",
    "numero_pasaporte": "103647370",
    "tipo": "P",
    "pais_emisor": "VEN",
    "nombre_completo": "ALDARA",
    "apellido_completo": "NAVARRO MASSEY",
    "fecha_nacimiento": "06/Jul/Jul/1985",
    "cedula": "76091115",
    "fecha_emision": "24/Jun/Jun/2023",
    "fecha_vencimiento": "24/Ene/Ene/2033",
    "sexo": "F",
    "nacionalidad": "VENEZOLANA",
    "lugar_nacimiento": "LA ASUNCION VEN",
    "codigo_verificacion": "06-07-85",
    "firma": "Al Nav",
    "fuente_firma": "White Sign (DemoVersion).otf",
    "mrz_linea1": "P<VENNAVARROMASSEY<<<<<<<<<ALDARA<<<<<<<<<<<",
    "mrz_linea2": "1036473701VEN850706F9501015<<<<<<<<<<<<<<<4<",
    "edad": 40,
    "correo_original": "ald4r4_n4v4rr0_06@outlook.com",
    "imagen_usada": "/media/warcklian/DATA_500GB/CODE/SISTEMA_PASAPORTES_FINAL/DATA/Imagenes_Mujeres/massive_venezuelan_mujer_40_3167_20251002_103828.png",
    "nombre_archivo": "ald4r4_n4v4rr0_06@outlook.com.png",
    "pasaporte_visual": "/media/warcklian/DATA_500GB/CODE/SISTEMA_PASAPORTES_FINAL/OUTPUT/pasaportes_visuales/ald4r4_n4v4rr0_06@outlook.com.png",
    "estado": "generado"
  },
  {
    "ruta_foto": "/media/warcklian/DATA_500GB/CODE/SISTEMA_PASAPORTES_FINAL/DATA/Imagenes_Mujeres/massive_venezuelan_mujer_33_3976_20251002_103828.png",
    "numero_pasaporte_1": "168889546",
    "numero_pasaporte_2": "168889546",
    "numero_pasaporte": "168889546",
    "tipo": "P",
    "pais_emisor": "VEN",
    "nombre_completo": "AILAMA",
    "apellido_completo": "BERMUDEZ PINTO",
    "fecha_nacimiento": "04/Jun/Jun/1992",
    "cedula": "82211431",
    "fecha_emision": "03/Abr/Abr/2021",
    "fecha_vencimiento": "03/Ene/Ene/2031",
    "sexo": "F",
    "nacionalidad": "VENEZOLANA",
    "lugar_nacimiento": "SAN JUAN DE LOS MORROS VEN",
    "codigo_verificacion": "04-06-92",
    "firma": "Ail Be",
    "fuente_firma": "White Sign (DemoVersion).otf",
    "mrz_linea1": "P<VENBERMUDEZPINTO<<<<<<<<<AILAMA<<<<<<<<<<<",
    "mrz_linea2": "1688895462VEN920604F0201010<<<<<<<<<<<<<<<1<",
    "edad": 33,
    "correo_original": "a1l4m4_b3rmud3z_04@hotmail.com",
    "imagen_usada": "/media/warcklian/DATA_500GB/CODE/SISTEMA_PASAPORTES_FINAL/DATA/Imagenes_Mujeres/massive_venezuelan_mujer_33_3976_20251002_103828.png",
    "nombre_archivo": "a1l4m4_b3rmud3z_04@hotmail.com.png",
    "pasaporte_visual": "/media/warcklian/DATA_500GB/CODE/SISTEMA_PASAPORTES_FINAL/OUTPUT/pasaportes_visuales/a1l4m4_b3rmud3z_04@hotmail.com.png",
    "estado": "generado"
  },
  {
    "ruta_foto": "/media/warcklian/DATA_500GB/CODE/SISTEMA_PASAPORTES_FINAL/DATA/Imagenes_Mujeres/massive_venezuelan_mujer_26_1796_20251002_103828.png",
    "numero_pasaporte_1": "126923769",
    "numero_pasaporte_2": "126923769",
    "numero_pasaporte": "126923769",
    "tipo": "P",
    "pais_emisor": "VEN",
    "nombre_completo": "BABETTE",
    "apellido_completo": "JOHNSON SERRANO",
    "fecha_nacimiento": "23/Oct/Oct/1998",
    "cedula": "84397399",
    "fecha_emision": "08/Jun/Jun/2020",
    "fecha_vencimiento": "08/Ene/Ene/2030",
    "sexo": "F",
    "nacionalidad": "VENEZOLANA",
    "lugar_nacimiento": "SAN FERNANDO DE APURE VEN",
    "codigo_verificacion": "23-10-98",
    "firma": "BabetteJ",
    "fuente_firma": "White Sign (DemoVersion).otf",
    "mrz_linea1": "P<VENJOHNSONSERRANO<<<<<<<<BABETTE<<<<<<<<<<",
    "mrz_linea2": "1269237697VEN981023F0801017<<<<<<<<<<<<<<<6<",
    "edad": 26,
    "correo_original": "b4b3tt3_j0hn50n_23@outlook.com",
    "imagen_usada": "/media/warcklian/DATA_500GB/CODE/SISTEMA_PASAPORTES_FINAL/DATA/Imagenes_Mujeres/massive_venezuelan_mujer_26_1796_20251002_103828.png",
    "nombre_archivo": "b4b3tt3_j0hn50n_23@outlook.com.png",
    "pasaporte_visual": "/media/warcklian/DATA_500GB/CODE/SISTEMA_PASAPORTES_FINAL/OUTPUT/pasaportes_visuales/b4b3tt3_j0hn50n_23@outlook.com.png",
    "estado": "generado"
  },
  {
    "ruta_foto": "/media/warcklian/DATA_500GB/CODE/SISTEMA_PASAPORTES_FINAL/DATA/Imagenes_Mujeres/massive_venezuelan_mujer_25_235_20250923_151733.png",
    "numero_pasaporte_1": "143343330",
    "numero_pasaporte_2": "143343330",
    "numero_pasaporte": "143343330",
    "tipo": "P",
    "pais_emisor": "VEN",
    "nombre_completo": "AGNES",
    "apellido_completo": "MENDIZABAL ESTEVEZ",
    "fecha_nacimiento": "03/Dic/Dic/1999",
    "cedula": "74927928",
    "fecha_emision": "29/Nov/Nov/2021",
    "fecha_vencimiento": "29/Ene/Ene/2031",
    "sexo": "F",
    "nacionalidad": "VENEZOLANA",
    "lugar_nacimiento": "MATURIN VEN",
    "codigo_verificacion": "03-12-99",
    "firma": "Mend A.",
    "fuente_firma": "White Sign (DemoVersion).otf",
    "mrz_linea1": "P<VENMENDIZABALESTEVEZ<<<<<AGNES<<<<<<<<<<<<",
    "mrz_linea2": "1433433300VEN991203F0901012<<<<<<<<<<<<<<<4<",
    "edad": 25,
    "correo_original": "agn35_m3nd1z4b4l_03@outlook.com",
    "imagen_usada": "/media/warcklian/DATA_500GB/CODE/SISTEMA_PASAPORTES_FINAL/DATA/Imagenes_Mujeres/massive_venezuelan_mujer_25_235_20250923_151733.png",
    "nombre_archivo": "agn35_m3nd1z4b4l_03@outlook.com.png",
    "pasaporte_visual": "/media/warcklian/DATA_500GB/CODE/SISTEMA_PASAPORTES_FINAL/OUTPUT/pasaportes_visuales/agn35_m3nd1z4b4l_03@outlook.com.png",
    "estado": "generado"
  },
  {
    "ruta_foto": "/media/warcklian/DATA_500GB/CODE/SISTEMA_PASAPORTES_FINAL/DATA/Imagenes_Mujeres/massive_venezuelan_mujer_43_415_20250930_114813.png",
    "numero_pasaporte_1": "142142553",
    "numero_pasaporte_2": "142142553",
    "numero_pasaporte": "142142553",
    "tipo": "P",
    "pais_emisor": "VEN",
    "nombre_completo": "AMANDA",
    "apellido_completo": "MORENO PUIG",
    "fecha_nacimiento": "14/Ago/Ago/1970",
    "cedula": "91055702",
    "fecha_emision": "15/Ago/Ago/2022",
    "fecha_vencimiento": "15/Ene/Ene/2032",
    "sexo": "F",
    "nacionalidad": "VENEZOLANA",
    "lugar_nacimiento": "BARQUISIMETO VEN",
    "codigo_verificacion": "14-08-70",
    "firma": "Aman-Mo",
    "fuente_firma": "White Sign (DemoVersion).otf",
    "mrz_linea1": "P<VENMORENOPUIG<<<<<<<<<<<<AMANDA<<<<<<<<<<<",
    "mrz_linea2": "1421425532VEN700814F8001016<<<<<<<<<<<<<<<6<",
    "edad": 55,
    "correo_original": "am4nd4_m0r3n0_14@hotmail.com",
    "imagen_usada": "/media/warcklian/DATA_500GB/CODE/SISTEMA_PASAPORTES_FINAL/DATA/Imagenes_Mujeres/massive_venezuelan_mujer_43_415_20250930_114813.png",
    "nombre_archivo": "am4nd4_m0r3n0_14@hotmail.com.png",
    "pasaporte_visual": "/media/warcklian/DATA_500GB/CODE/SISTEMA_PASAPORTES_FINAL/OUTPUT/pasaportes_visuales/am4nd4_m0r3n0_14@hotmail.com.png",
    "estado": "generado"
  },
  {
    "ruta_foto": "/media/warcklian/DATA_500GB/CODE/SISTEMA_PASAPORTES_FINAL/DATA/Imagenes_Mujeres/massive_venezuelan_mujer_40_2890_20251002_103828.png",
    "numero_pasaporte_1": "158782197",
    "numero_pasaporte_2": "158782197",
    "numero_pasaporte": "158782197",
    "tipo": "P",
    "pais_emisor": "VEN",
    "nombre_completo": "GLENNIA",
    "apellido_completo": "PAZ MARCANO",
    "fecha_nacimiento": "04/Ago/Ago/1968",
    "cedula": "74195492",
    "fecha_emision": "21/Jun/Jun/2020",
    "fecha_vencimiento": "21/Ene/Ene/2030",
    "sexo": "F",
    "nacionalidad": "VENEZOLANA",
    "lugar_nacimiento": "BARCELONA VEN",
    "codigo_verificacion": "04-08-68",
    "firma": "G. Pa",
    "fuente_firma": "White Sign (DemoVersion).otf",
    "mrz_linea1": "P<VENPAZMARCANO<<<<<<<<<<<<GLENNIA<<<<<<<<<<",
    "mrz_linea2": "1587821976VEN680804F7801018<<<<<<<<<<<<<<<6<",
    "edad": 57,
    "correo_original": "gl3nn14_p4z_04@outlook.com",
    "imagen_usada": "/media/warcklian/DATA_500GB/CODE/SISTEMA_PASAPORTES_FINAL/DATA/Imagenes_Mujeres/massive_venezuelan_mujer_40_2890_20251002_103828.png",
    "nombre_archivo": "gl3nn14_p4z_04@outlook.com.png",
    "pasaporte_visual": "/media/warcklian/DATA_500GB/CODE/SISTEMA_PASAPORTES_FINAL/OUTPUT/pasaportes_visuales/gl3nn14_p4z_04@outlook.com.png",
    "estado": "generado"
  },
  {
    "ruta_foto": "/media/warcklian/DATA_500GB/CODE/SISTEMA_PASAPORTES_FINAL/DATA/Imagenes_Mujeres/massive_venezuelan_mujer_32_318_20251002_184415.png",
    "numero_pasaporte_1": "196328385",
    "numero_pasaporte_2": "196328385",
    "numero_pasaporte": "196328385",
    "tipo": "P",
    "pais_emisor": "VEN",
    "nombre_completo": "NOELIA",
    "apellido_completo": "LAYU MCLEOD",
    "fecha_nacimiento": "24/Nov/Nov/1992",
    "cedula": "66405000",
    "fecha_emision": "13/Jun/Jun/2024",
    "fecha_vencimiento": "13/Ene/Ene/2034",
    "sexo": "F",
    "nacionalidad": "VENEZOLANA",
    "lugar_nacimiento": "SAN FELIPE VEN",
    "codigo_verificacion": "24-11-92",
    "firma": "Lay N.",
    "fuente_firma": "White Sign (DemoVersion).otf",
    "mrz_linea1": "P<VENLAYUMCLEOD<<<<<<<<<<<<NOELIA<<<<<<<<<<<",
    "mrz_linea2": "1963283854VEN921124F0201013<<<<<<<<<<<<<<<1<",
    "edad": 32,
    "correo_original": "n03l14_l4yu_24@hotmail.com",
    "imagen_usada": "/media/warcklian/DATA_500GB/CODE/SISTEMA_PASAPORTES_FINAL/DATA/Imagenes_Mujeres/massive_venezuelan_mujer_32_318_20251002_184415.png",
    "nombre_archivo": "n03l14_l4yu_24@hotmail.com.png",
    "pasaporte_visual": "/media/warcklian/DATA_500GB/CODE/SISTEMA_PASAPORTES_FINAL/OUTPUT/pasaportes_visuales/n03l14_l4yu_24@hotmail.com.png",
    "estado": "generado"
  },
  {
    "ruta_foto": "/media/warcklian/DATA_500GB/CODE/SISTEMA_PASAPORTES_FINAL/DATA/Imagenes_Mujeres/massive_venezuelan_mujer_24_748_20250929_164337.png",
    "numero_pasaporte_1": "117858220",
    "numero_pasaporte_2": "117858220",
    "numero_pasaporte": "117858220",
    "tipo": "P",
    "pais_emisor": "VEN",
    "nombre_completo": "CALIXTA",
    "apellido_completo": "SOUILHI ROMERA",
    "fecha_nacimiento": "16/May/May/2001",
    "cedula": "47231410",
    "fecha_emision": "04/Dic/Dic/2023",
    "fecha_vencimiento": "04/Ene/Ene/2033",
    "sexo": "F",
    "nacionalidad": "VENEZOLANA",
    "lugar_nacimiento": "MATURIN VEN",
    "codigo_verificacion": "16-05-01",
    "firma": "Cali-So",
    "fuente_firma": "White Sign (DemoVersion).otf",
    "mrz_linea1": "P<VENSOUILHIROMERA<<<<<<<<<CALIXTA<<<<<<<<<<",
    "mrz_linea2": "1178582206VEN010516F1101017<<<<<<<<<<<<<<<1<",
    "edad": 24,
    "correo_original": "c4l1xt4_50u1lh1_16@outlook.com",
    "imagen_usada": "/media/warcklian/DATA_500GB/CODE/SISTEMA_PASAPORTES_FINAL/DATA/Imagenes_Mujeres/massive_venezuelan_mujer_24_748_20250929_164337.png",
    "nombre_archivo": "c4l1xt4_50u1lh1_16@outlook.com.png",
    "pasaporte_visual": "/media/warcklian/DATA_500GB/CODE/SISTEMA_PASAPORTES_FINAL/OUTPUT/pasaportes_visuales/c4l1xt4_50u1lh1_16@outlook.com.png",
    "estado": "generado"
  },
  {
    "ruta_foto": "/media/warcklian/DATA_500GB/CODE/SISTEMA_PASAPORTES_FINAL/DATA/Imagenes_Mujeres/massive_venezuelan_mujer_29_2952_20251002_103828.png",
    "numero_pasaporte_1": "179179471",
    "numero_pasaporte_2": "179179471",
    "numero_pasaporte": "179179471",
    "tipo": "P",
    "pais_emisor": "VEN",
    "nombre_completo": "ISABELA",
    "apellido_completo": "HAILIE KNAPP",
    "fecha_nacimiento": "10/Ene/Ene/1996",
    "cedula": "34721713",
    "fecha_emision": "27/Ene/Ene/2025",
    "fecha_vencimiento": "27/Ene/Ene/2035",
    "sexo": "F",
    "nacionalidad": "VENEZOLANA",
    "lugar_nacimiento": "MARACAY VEN",
    "codigo_verificacion": "10-01-96",
    "firma": "Isabela Haili",
    "fuente_firma": "White Sign (DemoVersion).otf",
    "mrz_linea1": "P<VENHAILIEKNAPP<<<<<<<<<<<ISABELA<<<<<<<<<<",
    "mrz_linea2": "1791794715VEN960110F0601010<<<<<<<<<<<<<<<0<",
    "edad": 29,
    "correo_original": "i54b3l4_h41l13_10@outlook.com",
    "imagen_usada": "/media/warcklian/DATA_500GB/CODE/SISTEMA_PASAPORTES_FINAL/DATA/Imagenes_Mujeres/massive_venezuelan_mujer_29_2952_20251002_103828.png",
    "nombre_archivo": "i54b3l4_h41l13_10@outlook.com.png",
    "pasaporte_visual": "/media/warcklian/DATA_500GB/CODE/SISTEMA_PASAPORTES_FINAL/OUTPUT/pasaportes_visuales/i54b3l4_h41l13_10@outlook.com.png",
    "estado": "generado"
  },
  {
    "ruta_foto": "/media/warcklian/DATA_500GB/CODE/SISTEMA_PASAPORTES_FINAL/DATA/Imagenes_Mujeres/massive_venezuelan_mujer_31_3345_20251002_103828.png",
    "numero_pasaporte_1": "184570255",
    "numero_pasaporte_2": "184570255",
    "numero_pasaporte": "184570255",
    "tipo": "P",
    "pais_emisor": "VEN",
    "nombre_completo": "ERIEN",
    "apellido_completo": "VALENZUELA TORRE",
    "fecha_nacimiento": "23/Oct/Oct/1993",
    "cedula": "71798097",
    "fecha_emision": "02/Abr/Abr/2024",
    "fecha_vencimiento": "02/Ene/Ene/2034",
    "sexo": "F",
    "nacionalidad": "VENEZOLANA",
    "lugar_nacimiento": "LOS TEQUES VEN",
    "codigo_verificacion": "23-10-93",
    "firma": "Erien Valenzuela Torre",
    "fuente_firma": "White Sign (DemoVersion).otf",
    "mrz_linea1": "P<VENVALENZUELATORRE<<<<<<<ERIEN<<<<<<<<<<<<",
    "mrz_linea2": "1845702552VEN931023F0301019<<<<<<<<<<<<<<<9<",
    "edad": 31,
    "correo_original": "er13n_v4l3nzu3l4_23@hotmail.com",
    "imagen_usada": "/media/warcklian/DATA_500GB/CODE/SISTEMA_PASAPORTES_FINAL/DATA/Imagenes_Mujeres/massive_venezuelan_mujer_31_3345_20251002_103828.png",
    "nombre_archivo": "er13n_v4l3nzu3l4_23@hotmail.com.png",
    "pasaporte_visual": "/media/warcklian/DATA_500GB/CODE/SISTEMA_PASAPORTES_FINAL/OUTPUT/pasaportes_visuales/er13n_v4l3nzu3l4_23@hotmail.com.png",
    "estado": "generado"
  },
  {
    "ruta_foto": "/media/warcklian/DATA_500GB/CODE/SISTEMA_PASAPORTES_FINAL/DATA/Imagenes_Mujeres/massive_venezuelan_mujer_29_4213_20251002_103828.png",
    "numero_pasaporte_1": "164691291",
    "numero_pasaporte_2": "164691291",
    "numero_pasaporte": "164691291",
    "tipo": "P",
    "pais_emisor": "VEN",
    "nombre_completo": "GALA",
    "apellido_completo": "PASSO WEEKS",
    "fecha_nacimiento": "23/Jul/Jul/1996",
    "cedula": "49767159",
    "fecha_emision": "19/May/May/2021",
    "fecha_vencimiento": "19/Ene/Ene/2031",
    "sexo": "F",
    "nacionalidad": "VENEZOLANA",
    "lugar_nacimiento": "MATURIN VEN",
    "codigo_verificacion": "23-07-96",
    "firma": "Gala Pass",
    "fuente_firma": "White Sign (DemoVersion).otf",
    "mrz_linea1": "P<VENPASSOWEEKS<<<<<<<<<<<<GALA<<<<<<<<<<<<<",
    "mrz_linea2": "1646912919VEN960723F0601017<<<<<<<<<<<<<<<4<",
    "edad": 29,
    "correo_original": "g4l4_p4550_23@outlook.com",
    "imagen_usada": "/media/warcklian/DATA_500GB/CODE/SISTEMA_PASAPORTES_FINAL/DATA/Imagenes_Mujeres/massive_venezuelan_mujer_29_4213_20251002_103828.png",
    "nombre_archivo": "g4l4_p4550_23@outlook.com.png",
    "pasaporte_visual": "/media/warcklian/DATA_500GB/CODE/SISTEMA_PASAPORTES_FINAL/OUTPUT/pasaportes_visuales/g4l4_p4550_23@outlook.com.png",
    "estado": "generado"
  },
  {
    "ruta_foto": "/media/warcklian/DATA_500GB/CODE/SISTEMA_PASAPORTES_FINAL/DATA/Imagenes_Mujeres/massive_venezuelan_mujer_28_2512_20251002_103828.png",
    "numero_pasaporte_1": "123793587",
    "numero_pasaporte_2": "123793587",
    "numero_pasaporte": "123793587",
    "tipo": "P",
    "pais_emisor": "VEN",
    "nombre_completo": "JUSTICE",
    "apellido_completo": "JAMISON NORTON",
    "fecha_nacimiento": "04/Oct/Oct/1996",
    "cedula": "32523747",
    "fecha_emision": "13/May/May/2020",
    "fecha_vencimiento": "13/Ene/Ene/2030",
    "sexo": "F",
    "nacionalidad": "VENEZOLANA",
    "lugar_nacimiento": "SAN JUAN DE LOS MORROS VEN",
    "codigo_verificacion": "04-10-96",
    "firma": "Ju Jam",
    "fuente_firma": "White Sign (DemoVersion).otf",
    "mrz_linea1": "P<VENJAMISONNORTON<<<<<<<<<JUSTICE<<<<<<<<<<",
    "mrz_linea2": "1237935874VEN961004F0601018<<<<<<<<<<<<<<<5<",
    "edad": 28,
    "correo_original": "ju5t1c3_j4m150n_04@hotmail.com",
    "imagen_usada": "/media/warcklian/DATA_500GB/CODE/SISTEMA_PASAPORTES_FINAL/DATA/Imagenes_Mujeres/massive_venezuelan_mujer_28_2512_20251002_103828.png",
    "nombre_archivo": "ju5t1c3_j4m150n_04@hotmail.com.png",
    "pasaporte_visual": "/media/warcklian/DATA_500GB/CODE/SISTEMA_PASAPORTES_FINAL/OUTPUT/pasaportes_visuales/ju5t1c3_j4m150n_04@hotmail.com.png",
    "estado": "generado"
  },
  {
    "ruta_foto": "/media/warcklian/DATA_500GB/CODE/SISTEMA_PASAPORTES_FINAL/DATA/Imagenes_Mujeres/massive_venezuelan_mujer_25_2844_20251002_103828.png",
    "numero_pasaporte_1": "119447527",
    "numero_pasaporte_2": "119447527",
    "numero_pasaporte": "119447527",
    "tipo": "P",
    "pais_emisor": "VEN",
    "nombre_completo": "ELINAN",
    "apellido_completo": "MARIA VILLAR",
    "fecha_nacimiento": "18/Dic/Dic/1968",
    "cedula": "87398342",
    "fecha_emision": "20/Ago/Ago/2023",
    "fecha_vencimiento": "20/Ene/Ene/2033",
    "sexo": "F",
    "nacionalidad": "VENEZOLANA",
    "lugar_nacimiento": "BARCELONA VEN",
    "codigo_verificacion": "18-12-68",
    "firma": "Eli Mar",
    "fuente_firma": "White Sign (DemoVersion).otf",
    "mrz_linea1": "P<VENMARIAVILLAR<<<<<<<<<<<ELINAN<<<<<<<<<<<",
    "mrz_linea2": "1194475277VEN681218F7801016<<<<<<<<<<<<<<<4<",
    "edad": 56,
    "correo_original": "el1n4n_m4r14_18@hotmail.com",
    "imagen_usada": "/media/warcklian/DATA_500GB/CODE/SISTEMA_PASAPORTES_FINAL/DATA/Imagenes_Mujeres/massive_venezuelan_mujer_25_2844_20251002_103828.png",
    "nombre_archivo": "el1n4n_m4r14_18@hotmail.com.png",
    "pasaporte_visual": "/media/warcklian/DATA_500GB/CODE/SISTEMA_PASAPORTES_FINAL/OUTPUT/pasaportes_visuales/el1n4n_m4r14_18@hotmail.com.png",
    "estado": "generado"
  },
  {
    "ruta_foto": "/media/warcklian/DATA_500GB/CODE/SISTEMA_PASAPORTES_FINAL/DATA/Imagenes_Mujeres/massive_venezuelan_mujer_26_35_20251002_103828.png",
    "numero_pasaporte_1": "110427805",
    "numero_pasaporte_2": "110427805",
    "numero_pasaporte": "110427805",
    "tipo": "P",
    "pais_emisor": "VEN",
    "nombre_completo": "EULALIA",
    "apellido_completo": "COSTAS NIETO",
    "fecha_nacimiento": "25/May/May/1999",
    "cedula": "30720690",
    "fecha_emision": "21/Mar/Mar/2021",
    "fecha_vencimiento": "21/Ene/Ene/2031",
    "sexo": "F",
    "nacionalidad": "VENEZOLANA",
    "lugar_nacimiento": "BARCELONA VEN",
    "codigo_verificacion": "25-05-99",
    "firma": "Cost E",
    "fuente_firma": "White Sign (DemoVersion).otf",
    "mrz_linea1": "P<VENCOSTASNIETO<<<<<<<<<<<EULALIA<<<<<<<<<<",
    "mrz_linea2": "1104278053VEN990525F0901014<<<<<<<<<<<<<<<0<",
    "edad": 26,
    "correo_original": "eul4l14_c05t45_25@hotmail.com",
    "imagen_usada": "/media/warcklian/DATA_500GB/CODE/SISTEMA_PASAPORTES_FINAL/DATA/Imagenes_Mujeres/massive_venezuelan_mujer_26_35_20251002_103828.png",
    "nombre_archivo": "eul4l14_c05t45_25@hotmail.com.png",
    "pasaporte_visual": "/media/warcklian/DATA_500GB/CODE/SISTEMA_PASAPORTES_FINAL/OUTPUT/pasaportes_visuales/eul4l14_c05t45_25@hotmail.com.png",
    "estado": "generado"
  },
  {
    "ruta_foto": "/media/warcklian/DATA_500GB/CODE/SISTEMA_PASAPORTES_FINAL/DATA/Imagenes_Mujeres/massive_venezuelan_mujer_28_325_20250930_090804.png",
    "numero_pasaporte_1": "103679095",
    "numero_pasaporte_2": "103679095",
    "numero_pasaporte": "103679095",
    "tipo": "P",
    "pais_emisor": "VEN",
    "nombre_completo": "HARPER",
    "apellido_completo": "REYES GONZALEZ",
    "fecha_nacimiento": "18/Feb/Feb/1997",
    "cedula": "81070849",
    "fecha_emision": "10/Sep/Sep/2021",
    "fecha_vencimiento": "10/Ene/Ene/2031",
    "sexo": "F",
    "nacionalidad": "VENEZOLANA",
    "lugar_nacimiento": "SAN FELIPE VEN",
    "codigo_verificacion": "18-02-97",
    "firma": "HarperReyes Gonzalez",
    "fuente_firma": "White Sign (DemoVersion).otf",
    "mrz_linea1": "P<VENREYESGONZALEZ<<<<<<<<<HARPER<<<<<<<<<<<",
    "mrz_linea2": "1036790956VEN970218F0701010<<<<<<<<<<<<<<<7<",
    "edad": 28,
    "correo_original": "h4rp3r_r3y35_18@hotmail.com",
    "imagen_usada": "/media/warcklian/DATA_500GB/CODE/SISTEMA_PASAPORTES_FINAL/DATA/Imagenes_Mujeres/massive_venezuelan_mujer_28_325_20250930_090804.png",
    "nombre_archivo": "h4rp3r_r3y35_18@hotmail.com.png",
    "pasaporte_visual": "/media/warcklian/DATA_500GB/CODE/SISTEMA_PASAPORTES_FINAL/OUTPUT/pasaportes_visuales/h4rp3r_r3y35_18@hotmail.com.png",
    "estado": "generado"
  },
  {
    "ruta_foto": "/media/warcklian/DATA_500GB/CODE/SISTEMA_PASAPORTES_FINAL/DATA/Imagenes_Mujeres/massive_venezuelan_mujer_27_2001_20251002_103828.png",
    "numero_pasaporte_1": "159230964",
    "numero_pasaporte_2": "159230964",
    "numero_pasaporte": "159230964",
    "tipo": "P",
    "pais_emisor": "VEN",
    "nombre_completo": "ANABEL",
    "apellido_completo": "RHIANNA SHIPP",
    "fecha_nacimiento": "25/Jun/Jun/1998",
    "cedula": "43735050",
    "fecha_emision": "02/Feb/Feb/2020",
    "fecha_vencimiento": "02/Ene/Ene/2030",
    "sexo": "F",
    "nacionalidad": "VENEZOLANA",
    "lugar_nacimiento": "LA ASUNCION VEN",
    "codigo_verificacion": "25-06-98",
    "firma": "A. Rhianna Shipp",
    "fuente_firma": "White Sign (DemoVersion).otf",
    "mrz_linea1": "P<VENRHIANNASHIPP<<<<<<<<<<ANABEL<<<<<<<<<<<",
    "mrz_linea2": "1592309644VEN980625F0801011<<<<<<<<<<<<<<<7<",
    "edad": 27,
    "correo_original": "an4b3l_rh14nn4_25@outlook.com",
    "imagen_usada": "/media/warcklian/DATA_500GB/CODE/SISTEMA_PASAPORTES_FINAL/DATA/Imagenes_Mujeres/massive_venezuelan_mujer_27_2001_20251002_103828.png",
    "nombre_archivo": "an4b3l_rh14nn4_25@outlook.com.png",
    "pasaporte_visual": "/media/warcklian/DATA_500GB/CODE/SISTEMA_PASAPORTES_FINAL/OUTPUT/pasaportes_visuales/an4b3l_rh14nn4_25@outlook.com.png",
    "estado": "generado"
  },
  {
    "ruta_foto": "/media/warcklian/DATA_500GB/CODE/SISTEMA_PASAPORTES_FINAL/DATA/Imagenes_Mujeres/massive_venezuelan_mujer_36_1517_20250930_114813.png",
    "numero_pasaporte_1": "109401920",
    "numero_pasaporte_2": "109401920",
    "numero_pasaporte": "109401920",
    "tipo": "P",
    "pais_emisor": "VEN",
    "nombre_completo": "ALEXICA",
    "apellido_completo": "GIL ALVAREZ",
    "fecha_nacimiento": "30/Jun/Jun/1971",
    "cedula": "27619262",
    "fecha_emision": "25/Oct/Oct/2022",
    "fecha_vencimiento": "25/Ene/Ene/2032",
    "sexo": "F",
    "nacionalidad": "VENEZOLANA",
    "lugar_nacimiento": "MATURIN VEN",
    "codigo_verificacion": "30-06-71",
    "firma": "Gil  Al",
    "fuente_firma": "White Sign (DemoVersion).otf",
    "mrz_linea1": "P<VENGILALVAREZ<<<<<<<<<<<<ALEXICA<<<<<<<<<<",
    "mrz_linea2": "1094019208VEN710630F8101015<<<<<<<<<<<<<<<1<",
    "edad": 54,
    "correo_original": "al3x1c4_g1l_30@hotmail.com",
    "imagen_usada": "/media/warcklian/DATA_500GB/CODE/SISTEMA_PASAPORTES_FINAL/DATA/Imagenes_Mujeres/massive_venezuelan_mujer_36_1517_20250930_114813.png",
    "nombre_archivo": "al3x1c4_g1l_30@hotmail.com.png",
    "pasaporte_visual": "/media/warcklian/DATA_500GB/CODE/SISTEMA_PASAPORTES_FINAL/OUTPUT/pasaportes_visuales/al3x1c4_g1l_30@hotmail.com.png",
    "estado": "generado"
  },
  {
    "ruta_foto": "/media/warcklian/DATA_500GB/CODE/SISTEMA_PASAPORTES_FINAL/DATA/Imagenes_Mujeres/massive_venezuelan_mujer_31_1431_20250930_114813.png",
    "numero_pasaporte_1": "178903001",
    "numero_pasaporte_2": "178903001",
    "numero_pasaporte": "178903001",
    "tipo": "P",
    "pais_emisor": "VEN",
    "nombre_completo": "DARICE",
    "apellido_completo": "JULIA NIETO",
    "fecha_nacimiento": "10/Jul/Jul/1994",
    "cedula": "43040477",
    "fecha_emision": "29/Abr/Abr/2020",
    "fecha_vencimiento": "29/Ene/Ene/2030",
    "sexo": "F",
    "nacionalidad": "VENEZOLANA",
    "lugar_nacimiento": "VALENCIA VEN",
    "codigo_verificacion": "10-07-94",
    "firma": "Dar Jul",
    "fuente_firma": "White Sign (DemoVersion).otf",
    "mrz_linea1": "P<VENJULIANIETO<<<<<<<<<<<<DARICE<<<<<<<<<<<",
    "mrz_linea2": "1789030014VEN940710F0401019<<<<<<<<<<<<<<<1<",
    "edad": 31,
    "correo_original": "d4r1c3_jul14_10@outlook.com",
    "imagen_usada": "/media/warcklian/DATA_500GB/CODE/SISTEMA_PASAPORTES_FINAL/DATA/Imagenes_Mujeres/massive_venezuelan_mujer_31_1431_20250930_114813.png",
    "nombre_archivo": "d4r1c3_jul14_10@outlook.com.png",
    "pasaporte_visual": "/media/warcklian/DATA_500GB/CODE/SISTEMA_PASAPORTES_FINAL/OUTPUT/pasaportes_visuales/d4r1c3_jul14_10@outlook.com.png",
    "estado": "generado"
  },
  {
    "ruta_foto": "/media/warcklian/DATA_500GB/CODE/SISTEMA_PASAPORTES_FINAL/DATA/Imagenes_Mujeres/massive_venezuelan_mujer_42_156_20250930_104411.png",
    "numero_pasaporte_1": "166265300",
    "numero_pasaporte_2": "166265300",
    "numero_pasaporte": "166265300",
    "tipo": "P",
    "pais_emisor": "VEN",
    "nombre_completo": "KIERSTEN",
    "apellido_completo": "CAROLINA AGUIRRE",
    "fecha_nacimiento": "03/Ago/Ago/1983",
    "cedula": "58909253",
    "fecha_emision": "23/Feb/Feb/2024",
    "fecha_vencimiento": "23/Ene/Ene/2034",
    "sexo": "F",
    "nacionalidad": "VENEZOLANA",
    "lugar_nacimiento": "GUANARE VEN",
    "codigo_verificacion": "03-08-83",
    "firma": "Caro K.",
    "fuente_firma": "White Sign (DemoVersion).otf",
    "mrz_linea1": "P<VENCAROLINAAGUIRRE<<<<<<<KIERSTEN<<<<<<<<<",
    "mrz_linea2": "1662653000VEN830803F9301016<<<<<<<<<<<<<<<0<",
    "edad": 42,
    "correo_original": "k13r5t3n_c4r0l1n4_03@outlook.com",
    "imagen_usada": "/media/warcklian/DATA_500GB/CODE/SISTEMA_PASAPORTES_FINAL/DATA/Imagenes_Mujeres/massive_venezuelan_mujer_42_156_20250930_104411.png",
    "nombre_archivo": "k13r5t3n_c4r0l1n4_03@outlook.com.png",
    "pasaporte_visual": "/media/warcklian/DATA_500GB/CODE/SISTEMA_PASAPORTES_FINAL/OUTPUT/pasaportes_visuales/k13r5t3n_c4r0l1n4_03@outlook.com.png",
    "estado": "generado"
  },
  {
    "ruta_foto": "/media/warcklian/DATA_500GB/CODE/SISTEMA_PASAPORTES_FINAL/DATA/Imagenes_Mujeres/massive_venezuelan_mujer_41_2682_20251002_103828.png",
    "numero_pasaporte_1": "197625410",
    "numero_pasaporte_2": "197625410",
    "numero_pasaporte": "197625410",
    "tipo": "P",
    "pais_emisor": "VEN",
    "nombre_completo": "MARISABEL",
    "apellido_completo": "QUINTERO GALLEGO",
    "fecha_nacimiento": "22/Dic/Dic/1964",
    "cedula": "29023456",
    "fecha_emision": "22/Dic/Dic/2021",
    "fecha_vencimiento": "22/Ene/Ene/2031",
    "sexo": "F",
    "nacionalidad": "VENEZOLANA",
    "lugar_nacimiento": "TUCUPITA VEN",
    "codigo_verificacion": "22-12-64",
    "firma": "Mari. Quintero Gallego",
    "fuente_firma": "White Sign (DemoVersion).otf",
    "mrz_linea1": "P<VENQUINTEROGALLEGO<<<<<<<MARISABEL<<<<<<<<",
    "mrz_linea2": "1976254100VEN641222F7401018<<<<<<<<<<<<<<<8<",
    "edad": 60,
    "correo_original": "m4r154b3l_qu1nt3r0_22@hotmail.com",
    "imagen_usada": "/media/warcklian/DATA_500GB/CODE/SISTEMA_PASAPORTES_FINAL/DATA/Imagenes_Mujeres/massive_venezuelan_mujer_41_2682_20251002_103828.png",
    "nombre_archivo": "m4r154b3l_qu1nt3r0_22@hotmail.com.png",
    "pasaporte_visual": "/media/warcklian/DATA_500GB/CODE/SISTEMA_PASAPORTES_FINAL/OUTPUT/pasaportes_visuales/m4r154b3l_qu1nt3r0_22@hotmail.com.png",
    "estado": "generado"
  },
  {
    "ruta_foto": "/media/warcklian/DATA_500GB/CODE/SISTEMA_PASAPORTES_FINAL/DATA/Imagenes_Mujeres/massive_venezuelan_mujer_48_738_20250930_114813.png",
    "numero_pasaporte_1": "100346110",
    "numero_pasaporte_2": "100346110",
    "numero_pasaporte": "100346110",
    "tipo": "P",
    "pais_emisor": "VEN",
    "nombre_completo": "ARIANNA",
    "apellido_completo": "CAMPO FERNANDEZ",
    "fecha_nacimiento": "20/Ene/Ene/1977",
    "cedula": "46758952",
    "fecha_emision": "08/Dic/Dic/2021",
    "fecha_vencimiento": "08/Ene/Ene/2031",
    "sexo": "F",
    "nacionalidad": "VENEZOLANA",
    "lugar_nacimiento": "BARINAS VEN",
    "codigo_verificacion": "20-01-77",
    "firma": "Ar Cam",
    "fuente_firma": "White Sign (DemoVersion).otf",
    "mrz_linea1": "P<VENCAMPOFERNANDEZ<<<<<<<<ARIANNA<<<<<<<<<<",
    "mrz_linea2": "1003461106VEN770120F8701018<<<<<<<<<<<<<<<7<",
    "edad": 48,
    "correo_original": "ar14nn4_c4mp0_20@outlook.com",
    "imagen_usada": "/media/warcklian/DATA_500GB/CODE/SISTEMA_PASAPORTES_FINAL/DATA/Imagenes_Mujeres/massive_venezuelan_mujer_48_738_20250930_114813.png",
    "nombre_archivo": "ar14nn4_c4mp0_20@outlook.com.png",
    "pasaporte_visual": "/media/warcklian/DATA_500GB/CODE/SISTEMA_PASAPORTES_FINAL/OUTPUT/pasaportes_visuales/ar14nn4_c4mp0_20@outlook.com.png",
    "estado": "generado"
  },
  {
    "ruta_foto": "/media/warcklian/DATA_500GB/CODE/SISTEMA_PASAPORTES_FINAL/DATA/Imagenes_Mujeres/massive_venezuelan_mujer_44_1038_20251002_184415.png",
    "numero_pasaporte_1": "190868131",
    "numero_pasaporte_2": "190868131",
    "numero_pasaporte": "190868131",
    "tipo": "P",
    "pais_emisor": "VEN",
    "nombre_completo": "MELANIE",
    "apellido_completo": "EVELYN PARENT",
    "fecha_nacimiento": "25/Jul/Jul/1981",
    "cedula": "44175057",
    "fecha_emision": "05/Ago/Ago/2020",
    "fecha_vencimiento": "05/Ene/Ene/2030",
    "sexo": "F",
    "nacionalidad": "VENEZOLANA",
    "lugar_nacimiento": "SAN JUAN DE LOS MORROS VEN",
    "codigo_verificacion": "25-07-81",
    "firma": "Evel Me",
    "fuente_firma": "White Sign (DemoVersion).otf",
    "mrz_linea1": "P<VENEVELYNPARENT<<<<<<<<<<MELANIE<<<<<<<<<<",
    "mrz_linea2": "1908681311VEN810725F9101018<<<<<<<<<<<<<<<9<",
    "edad": 44,
    "correo_original": "m3l4n13_3v3lyn_25@hotmail.com",
    "imagen_usada": "/media/warcklian/DATA_500GB/CODE/SISTEMA_PASAPORTES_FINAL/DATA/Imagenes_Mujeres/massive_venezuelan_mujer_44_1038_20251002_184415.png",
    "nombre_archivo": "m3l4n13_3v3lyn_25@hotmail.com.png",
    "pasaporte_visual": "/media/warcklian/DATA_500GB/CODE/SISTEMA_PASAPORTES_FINAL/OUTPUT/pasaportes_visuales/m3l4n13_3v3lyn_25@hotmail.com.png",
    "estado": "generado"
  },
  {
    "ruta_foto": "/media/warcklian/DATA_500GB/CODE/SISTEMA_PASAPORTES_FINAL/DATA/Imagenes_Mujeres/massive_venezuelan_mujer_31_645_20250930_090804.png",
    "numero_pasaporte_1": "164878237",
    "numero_pasaporte_2": "164878237",
    "numero_pasaporte": "164878237",
    "tipo": "P",
    "pais_emisor": "VEN",
    "nombre_completo": "MARIA",
    "apellido_completo": "EL AASRAOUI",
    "fecha_nacimiento": "19/May/May/1994",
    "cedula": "67461848",
    "fecha_emision": "05/May/May/2024",
    "fecha_vencimiento": "05/Ene/Ene/2034",
    "sexo": "F",
    "nacionalidad": "VENEZOLANA",
    "lugar_nacimiento": "BARCELONA VEN",
    "codigo_verificacion": "19-05-94",
    "firma": "El  M",
    "fuente_firma": "White Sign (DemoVersion).otf",
    "mrz_linea1": "P<VENELAASRAOUI<<<<<<<<<<<<MARIA<<<<<<<<<<<<",
    "mrz_linea2": "1648782370VEN940519F0401018<<<<<<<<<<<<<<<5<",
    "edad": 31,
    "correo_original": "m4r14_3l_19@outlook.com",
    "imagen_usada": "/media/warcklian/DATA_500GB/CODE/SISTEMA_PASAPORTES_FINAL/DATA/Imagenes_Mujeres/massive_venezuelan_mujer_31_645_20250930_090804.png",
    "nombre_archivo": "m4r14_3l_19@outlook.com.png",
    "pasaporte_visual": "/media/warcklian/DATA_500GB/CODE/SISTEMA_PASAPORTES_FINAL/OUTPUT/pasaportes_visuales/m4r14_3l_19@outlook.com.png",
    "estado": "generado"
  },
  {
    "ruta_foto": "/media/warcklian/DATA_500GB/CODE/SISTEMA_PASAPORTES_FINAL/DATA/Imagenes_Mujeres/massive_venezuelan_mujer_30_505_20251002_103828.png",
    "numero_pasaporte_1": "183152758",
    "numero_pasaporte_2": "183152758",
    "numero_pasaporte": "183152758",
    "tipo": "P",
    "pais_emisor": "VEN",
    "nombre_completo": "LAUREL",
    "apellido_completo": "LAUREARA REDD",
    "fecha_nacimiento": "18/May/May/1995",
    "cedula": "99451868",
    "fecha_emision": "08/Ene/Ene/2021",
    "fecha_vencimiento": "08/Ene/Ene/2031",
    "sexo": "F",
    "nacionalidad": "VENEZOLANA",
    "lugar_nacimiento": "CORO VEN",
    "codigo_verificacion": "18-05-95",
    "firma": "L. Laure",
    "fuente_firma": "White Sign (DemoVersion).otf",
    "mrz_linea1": "P<VENLAUREARAREDD<<<<<<<<<<LAUREL<<<<<<<<<<<",
    "mrz_linea2": "1831527583VEN950518F0501013<<<<<<<<<<<<<<<5<",
    "edad": 30,
    "correo_original": "l4ur3l_l4ur34r4_18@hotmail.com",
    "imagen_usada": "/media/warcklian/DATA_500GB/CODE/SISTEMA_PASAPORTES_FINAL/DATA/Imagenes_Mujeres/massive_venezuelan_mujer_30_505_20251002_103828.png",
    "nombre_archivo": "l4ur3l_l4ur34r4_18@hotmail.com.png",
    "pasaporte_visual": "/media/warcklian/DATA_500GB/CODE/SISTEMA_PASAPORTES_FINAL/OUTPUT/pasaportes_visuales/l4ur3l_l4ur34r4_18@hotmail.com.png",
    "estado": "generado"
  },
  {
    "ruta_foto": "/media/warcklian/DATA_500GB/CODE/SISTEMA_PASAPORTES_FINAL/DATA/Imagenes_Mujeres/massive_venezuelan_mujer_26_507_20250929_164337.png",
    "numero_pasaporte_1": "106174630",
    "numero_pasaporte_2": "106174630",
    "numero_pasaporte": "106174630",
    "tipo": "P",
    "pais_emisor": "VEN",
    "nombre_completo": "LARISSA",
    "apellido_completo": "MARTINEZ FERREIRA",
    "fecha_nacimiento": "06/Nov/Nov/1998",
    "cedula": "60114179",
    "fecha_emision": "08/Dic/Dic/2020",
    "fecha_vencimiento": "08/Ene/Ene/2030",
    "sexo": "F",
    "nacionalidad": "VENEZOLANA",
    "lugar_nacimiento": "TRUJILLO VEN",
    "codigo_verificacion": "06-11-98",
    "firma": "Lar Mart",
    "fuente_firma": "White Sign (DemoVersion).otf",
    "mrz_linea1": "P<VENMARTINEZFERREIRA<<<<<<LARISSA<<<<<<<<<<",
    "mrz_linea2": "1061746301VEN981106F0801017<<<<<<<<<<<<<<<0<",
    "edad": 26,
    "correo_original": "l4r1554_m4rt1n3z_06@outlook.com",
    "imagen_usada": "/media/warcklian/DATA_500GB/CODE/SISTEMA_PASAPORTES_FINAL/DATA/Imagenes_Mujeres/massive_venezuelan_mujer_26_507_20250929_164337.png",
    "nombre_archivo": "l4r1554_m4rt1n3z_06@outlook.com.png",
    "pasaporte_visual": "/media/warcklian/DATA_500GB/CODE/SISTEMA_PASAPORTES_FINAL/OUTPUT/pasaportes_visuales/l4r1554_m4rt1n3z_06@outlook.com.png",
    "estado": "generado"
  },
  {
    "ruta_foto": "/media/warcklian/DATA_500GB/CODE/SISTEMA_PASAPORTES_FINAL/DATA/Imagenes_Mujeres/massive_venezuelan_mujer_43_1143_20250930_171727.png",
    "numero_pasaporte_1": "190758682",
    "numero_pasaporte_2": "190758682",
    "numero_pasaporte": "190758682",
    "tipo": "P",
    "pais_emisor": "VEN",
    "nombre_completo": "FARRAH",
    "apellido_completo": "BAYLEE KNUTSON",
    "fecha_nacimiento": "18/Jul/Jul/1982",
    "cedula": "21831599",
    "fecha_emision": "26/Ene/Ene/2023",
    "fecha_vencimiento": "26/Ene/Ene/2033",
    "sexo": "F",
    "nacionalidad": "VENEZOLANA",
    "lugar_nacimiento": "CIUDAD BOLIVAR VEN",
    "codigo_verificacion": "18-07-82",
    "firma": "Farr Ba",
    "fuente_firma": "White Sign (DemoVersion).otf",
    "mrz_linea1": "P<VENBAYLEEKNUTSON<<<<<<<<<FARRAH<<<<<<<<<<<",
    "mrz_linea2": "1907586824VEN820718F9201016<<<<<<<<<<<<<<<0<",
    "edad": 43,
    "correo_original": "f4rr4h_b4yl33_18@hotmail.com",
    "imagen_usada": "/media/warcklian/DATA_500GB/CODE/SISTEMA_PASAPORTES_FINAL/DATA/Imagenes_Mujeres/massive_venezuelan_mujer_43_1143_20250930_171727.png",
    "nombre_archivo": "f4rr4h_b4yl33_18@hotmail.com.png",
    "pasaporte_visual": "/media/warcklian/DATA_500GB/CODE/SISTEMA_PASAPORTES_FINAL/OUTPUT/pasaportes_visuales/f4rr4h_b4yl33_18@hotmail.com.png",
    "estado": "generado"
  },
  {
    "ruta_foto": "/media/warcklian/DATA_500GB/CODE/SISTEMA_PASAPORTES_FINAL/DATA/Imagenes_Mujeres/massive_venezuelan_mujer_39_840_20251002_103828.png",
    "numero_pasaporte_1": "162004590",
    "numero_pasaporte_2": "162004590",
    "numero_pasaporte": "162004590",
    "tipo": "P",
    "pais_emisor": "VEN",
    "nombre_completo": "ANAHI",
    "apellido_completo": "VANG ZABALETA",
    "fecha_nacimiento": "24/Jul/Jul/1986",
    "cedula": "32561148",
    "fecha_emision": "04/Abr/Abr/2020",
    "fecha_vencimiento": "04/Ene/Ene/2030",
    "sexo": "F",
    "nacionalidad": "VENEZOLANA",
    "lugar_nacimiento": "SAN JUAN DE LOS MORROS VEN",
    "codigo_verificacion": "24-07-86",
    "firma": "A-Vang Zabaleta",
    "fuente_firma": "White Sign (DemoVersion).otf",
    "mrz_linea1": "P<VENVANGZABALETA<<<<<<<<<<ANAHI<<<<<<<<<<<<",
    "mrz_linea2": "1620045903VEN860724F9601017<<<<<<<<<<<<<<<5<",
    "edad": 39,
    "correo_original": "an4h1_v4ng_24@hotmail.com",
    "imagen_usada": "/media/warcklian/DATA_500GB/CODE/SISTEMA_PASAPORTES_FINAL/DATA/Imagenes_Mujeres/massive_venezuelan_mujer_39_840_20251002_103828.png",
    "nombre_archivo": "an4h1_v4ng_24@hotmail.com.png",
    "pasaporte_visual": "/media/warcklian/DATA_500GB/CODE/SISTEMA_PASAPORTES_FINAL/OUTPUT/pasaportes_visuales/an4h1_v4ng_24@hotmail.com.png",
    "estado": "generado"
  },
  {
    "ruta_foto": "/media/warcklian/DATA_500GB/CODE/SISTEMA_PASAPORTES_FINAL/DATA/Imagenes_Mujeres/massive_venezuelan_mujer_31_2309_20251002_103828.png",
    "numero_pasaporte_1": "171170117",
    "numero_pasaporte_2": "171170117",
    "numero_pasaporte": "171170117",
    "tipo": "P",
    "pais_emisor": "VEN",
    "nombre_completo": "SARA",
    "apellido_completo": "SANZ FIORE",
    "fecha_nacimiento": "06/Nov/Nov/1993",
    "cedula": "87488428",
    "fecha_emision": "29/Mar/Mar/2021",
    "fecha_vencimiento": "29/Ene/Ene/2031",
    "sexo": "F",
    "nacionalidad": "VENEZOLANA",
    "lugar_nacimiento": "SAN JUAN DE LOS MORROS VEN",
    "codigo_verificacion": "06-11-93",
    "firma": "SarSanz Fiore",
    "fuente_firma": "White Sign (DemoVersion).otf",
    "mrz_linea1": "P<VENSANZFIORE<<<<<<<<<<<<<SARA<<<<<<<<<<<<<",
    "mrz_linea2": "1711701172VEN931106F0301013<<<<<<<<<<<<<<<8<",
    "edad": 31,
    "correo_original": "s4r4_54nz_06@outlook.com",
    "imagen_usada": "/media/warcklian/DATA_500GB/CODE/SISTEMA_PASAPORTES_FINAL/DATA/Imagenes_Mujeres/massive_venezuelan_mujer_31_2309_20251002_103828.png",
    "nombre_archivo": "s4r4_54nz_06@outlook.com.png",
    "pasaporte_visual": "/media/warcklian/DATA_500GB/CODE/SISTEMA_PASAPORTES_FINAL/OUTPUT/pasaportes_visuales/s4r4_54nz_06@outlook.com.png",
    "estado": "generado"
  },
  {
    "ruta_foto": "/media/warcklian/DATA_500GB/CODE/SISTEMA_PASAPORTES_FINAL/DATA/Imagenes_Mujeres/massive_venezuelan_mujer_29_298_20251002_184415.png",
    "numero_pasaporte_1": "175592258",
    "numero_pasaporte_2": "175592258",
    "numero_pasaporte": "175592258",
    "tipo": "P",
    "pais_emisor": "VEN",
    "nombre_completo": "KRISTIN",
    "apellido_completo": "XIMENA WHIPPLE",
    "fecha_nacimiento": "07/Nov/Nov/1995",
    "cedula": "85948405",
    "fecha_emision": "30/May/May/2020",
    "fecha_vencimiento": "30/Ene/Ene/2030",
    "sexo": "F",
    "nacionalidad": "VENEZOLANA",
    "lugar_nacimiento": "SAN FELIPE VEN",
    "codigo_verificacion": "07-11-95",
    "firma": "K. Xime",
    "fuente_firma": "White Sign (DemoVersion).otf",
    "mrz_linea1": "P<VENXIMENAWHIPPLE<<<<<<<<<KRISTIN<<<<<<<<<<",
    "mrz_linea2": "1755922587VEN951107F0501013<<<<<<<<<<<<<<<0<",
    "edad": 29,
    "correo_original": "kr15t1n_x1m3n4_07@hotmail.com",
    "imagen_usada": "/media/warcklian/DATA_500GB/CODE/SISTEMA_PASAPORTES_FINAL/DATA/Imagenes_Mujeres/massive_venezuelan_mujer_29_298_20251002_184415.png",
    "nombre_archivo": "kr15t1n_x1m3n4_07@hotmail.com.png",
    "pasaporte_visual": "/media/warcklian/DATA_500GB/CODE/SISTEMA_PASAPORTES_FINAL/OUTPUT/pasaportes_visuales/kr15t1n_x1m3n4_07@hotmail.com.png",
    "estado": "generado"
  },
  {
    "ruta_foto": "/media/warcklian/DATA_500GB/CODE/SISTEMA_PASAPORTES_FINAL/DATA/Imagenes_Mujeres/massive_venezuelan_mujer_29_3428_20251002_103828.png",
    "numero_pasaporte_1": "170708447",
    "numero_pasaporte_2": "170708447",
    "numero_pasaporte": "170708447",
    "tipo": "P",
    "pais_emisor": "VEN",
    "nombre_completo": "YRAIDA",
    "apellido_completo": "CORRALES MCCANN",
    "fecha_nacimiento": "03/Jul/Jul/1996",
    "cedula": "65471513",
    "fecha_emision": "12/Ago/Ago/2024",
    "fecha_vencimiento": "12/Ene/Ene/2034",
    "sexo": "F",
    "nacionalidad": "VENEZOLANA",
    "lugar_nacimiento": "TUCUPITA VEN",
    "codigo_verificacion": "03-07-96",
    "firma": "Yrai C",
    "fuente_firma": "White Sign (DemoVersion).otf",
    "mrz_linea1": "P<VENCORRALESMCCANN<<<<<<<<YRAIDA<<<<<<<<<<<",
    "mrz_linea2": "1707084478VEN960703F0601013<<<<<<<<<<<<<<<4<",
    "edad": 29,
    "correo_original": "yr41d4_c0rr4l35_03@hotmail.com",
    "imagen_usada": "/media/warcklian/DATA_500GB/CODE/SISTEMA_PASAPORTES_FINAL/DATA/Imagenes_Mujeres/massive_venezuelan_mujer_29_3428_20251002_103828.png",
    "nombre_archivo": "yr41d4_c0rr4l35_03@hotmail.com.png",
    "pasaporte_visual": "/media/warcklian/DATA_500GB/CODE/SISTEMA_PASAPORTES_FINAL/OUTPUT/pasaportes_visuales/yr41d4_c0rr4l35_03@hotmail.com.png",
    "estado": "generado"
  },
  {
    "ruta_foto": "/media/warcklian/DATA_500GB/CODE/SISTEMA_PASAPORTES_FINAL/DATA/Imagenes_Mujeres/massive_venezuelan_mujer_26_2052_20251002_103828.png",
    "numero_pasaporte_1": "170768494",
    "numero_pasaporte_2": "170768494",
    "numero_pasaporte": "170768494",
    "tipo": "P",
    "pais_emisor": "VEN",
    "nombre_completo": "NIKOLE",
    "apellido_completo": "MOHAMED BERMEJO",
    "fecha_nacimiento": "25/Abr/Abr/1999",
    "cedula": "37581700",
    "fecha_emision": "26/Ago/Ago/2022",
    "fecha_vencimiento": "26/Ene/Ene/2032",
    "sexo": "F",
    "nacionalidad": "VENEZOLANA",
    "lugar_nacimiento": "SAN FELIPE VEN",
    "codigo_verificacion": "25-04-99",
    "firma": "M. Nikole",
    "fuente_firma": "White Sign (DemoVersion).otf",
    "mrz_linea1": "P<VENMOHAMEDBERMEJO<<<<<<<<NIKOLE<<<<<<<<<<<",
    "mrz_linea2": "1707684941VEN990425F0901012<<<<<<<<<<<<<<<3<",
    "edad": 26,
    "correo_original": "n1k0l3_m0h4m3d_25@outlook.com",
    "imagen_usada": "/media/warcklian/DATA_500GB/CODE/SISTEMA_PASAPORTES_FINAL/DATA/Imagenes_Mujeres/massive_venezuelan_mujer_26_2052_20251002_103828.png",
    "nombre_archivo": "n1k0l3_m0h4m3d_25@outlook.com.png",
    "pasaporte_visual": "/media/warcklian/DATA_500GB/CODE/SISTEMA_PASAPORTES_FINAL/OUTPUT/pasaportes_visuales/n1k0l3_m0h4m3d_25@outlook.com.png",
    "estado": "generado"
  },
  {
    "ruta_foto": "/media/warcklian/DATA_500GB/CODE/SISTEMA_PASAPORTES_FINAL/DATA/Imagenes_Mujeres/massive_venezuelan_mujer_47_3_20250923_200515.png",
    "numero_pasaporte_1": "164949594",
    "numero_pasaporte_2": "164949594",
    "numero_pasaporte": "164949594",
    "tipo": "P",
    "pais_emisor": "VEN",
    "nombre_completo": "MARIBELL",
    "apellido_completo": "MUNOZ ROMERO",
    "fecha_nacimiento": "30/May/May/1978",
    "cedula": "90230812",
    "fecha_emision": "15/Jun/Jun/2025",
    "fecha_vencimiento": "15/Ene/Ene/2035",
    "sexo": "F",
    "nacionalidad": "VENEZOLANA",
    "lugar_nacimiento": "TRUJILLO VEN",
    "codigo_verificacion": "30-05-78",
    "firma": "Mar Mun",
    "fuente_firma": "White Sign (DemoVersion).otf",
    "mrz_linea1": "P<VENMUNOZROMERO<<<<<<<<<<<MARIBELL<<<<<<<<<",
    "mrz_linea2": "1649495945VEN780530F8801011<<<<<<<<<<<<<<<3<",
    "edad": 47,
    "correo_original": "m4r1b3ll_mun0z_30@outlook.com",
    "imagen_usada": "/media/warcklian/DATA_500GB/CODE/SISTEMA_PASAPORTES_FINAL/DATA/Imagenes_Mujeres/massive_venezuelan_mujer_47_3_20250923_200515.png",
    "nombre_archivo": "m4r1b3ll_mun0z_30@outlook.com.png",
    "pasaporte_visual": "/media/warcklian/DATA_500GB/CODE/SISTEMA_PASAPORTES_FINAL/OUTPUT/pasaportes_visuales/m4r1b3ll_mun0z_30@outlook.com.png",
    "estado": "generado"
  },
  {
    "ruta_foto": "/media/warcklian/DATA_500GB/CODE/SISTEMA_PASAPORTES_FINAL/DATA/Imagenes_Mujeres/massive_venezuelan_mujer_25_588_20251002_103828.png",
    "numero_pasaporte_1": "198957609",
    "numero_pasaporte_2": "198957609",
    "numero_pasaporte": "198957609",
    "tipo": "P",
    "pais_emisor": "VEN",
    "nombre_completo": "JANETH",
    "apellido_completo": "LIKONA ORTEGA",
    "fecha_nacimiento": "02/Oct/Oct/1972",
    "cedula": "79514926",
    "fecha_emision": "23/Mar/Mar/2024",
    "fecha_vencimiento": "23/Ene/Ene/2034",
    "sexo": "F",
    "nacionalidad": "VENEZOLANA",
    "lugar_nacimiento": "TRUJILLO VEN",
    "codigo_verificacion": "02-10-72",
    "firma": "J. Likona Ortega",
    "fuente_firma": "White Sign (DemoVersion).otf",
    "mrz_linea1": "P<VENLIKONAORTEGA<<<<<<<<<<JANETH<<<<<<<<<<<",
    "mrz_linea2": "1989576093VEN721002F8201012<<<<<<<<<<<<<<<2<",
    "edad": 53,
    "correo_original": "j4n3th_l1k0n4_02@hotmail.com",
    "imagen_usada": "/media/warcklian/DATA_500GB/CODE/SISTEMA_PASAPORTES_FINAL/DATA/Imagenes_Mujeres/massive_venezuelan_mujer_25_588_20251002_103828.png",
    "nombre_archivo": "j4n3th_l1k0n4_02@hotmail.com.png",
    "pasaporte_visual": "/media/warcklian/DATA_500GB/CODE/SISTEMA_PASAPORTES_FINAL/OUTPUT/pasaportes_visuales/j4n3th_l1k0n4_02@hotmail.com.png",
    "estado": "generado"
  },
  {
    "ruta_foto": "/media/warcklian/DATA_500GB/CODE/SISTEMA_PASAPORTES_FINAL/DATA/Imagenes_Mujeres/massive_venezuelan_mujer_24_163_20250930_090804.png",
    "numero_pasaporte_1": "164912980",
    "numero_pasaporte_2": "164912980",
    "numero_pasaporte": "164912980",
    "tipo": "P",
    "pais_emisor": "VEN",
    "nombre_completo": "VERONICA",
    "apellido_completo": "ESCUJURI IBANEZ",
    "fecha_nacimiento": "09/Oct/Oct/1971",
    "cedula": "83447026",
    "fecha_emision": "29/Nov/Nov/2021",
    "fecha_vencimiento": "29/Ene/Ene/2031",
    "sexo": "F",
    "nacionalidad": "VENEZOLANA",
    "lugar_nacimiento": "BARQUISIMETO VEN",
    "codigo_verificacion": "09-10-71",
    "firma": "Ve. Escujuri Ibanez",
    "fuente_firma": "White Sign (DemoVersion).otf",
    "mrz_linea1": "P<VENESCUJURIIBANEZ<<<<<<<<VERONICA<<<<<<<<<",
    "mrz_linea2": "1649129809VEN711009F8101019<<<<<<<<<<<<<<<6<",
    "edad": 53,
    "correo_original": "v3r0n1c4_35cujur1_09@outlook.com",
    "imagen_usada": "/media/warcklian/DATA_500GB/CODE/SISTEMA_PASAPORTES_FINAL/DATA/Imagenes_Mujeres/massive_venezuelan_mujer_24_163_20250930_090804.png",
    "nombre_archivo": "v3r0n1c4_35cujur1_09@outlook.com.png",
    "pasaporte_visual": "/media/warcklian/DATA_500GB/CODE/SISTEMA_PASAPORTES_FINAL/OUTPUT/pasaportes_visuales/v3r0n1c4_35cujur1_09@outlook.com.png",
    "estado": "generado"
  },
  {
    "ruta_foto": "/media/warcklian/DATA_500GB/CODE/SISTEMA_PASAPORTES_FINAL/DATA/Imagenes_Mujeres/massive_venezuelan_mujer_26_4042_20251002_103828.png",
    "numero_pasaporte_1": "120910597",
    "numero_pasaporte_2": "120910597",
    "numero_pasaporte": "120910597",
    "tipo": "P",
    "pais_emisor": "VEN",
    "nombre_completo": "ROKSANA",
    "apellido_completo": "GUENTHER DOMENECH",
    "fecha_nacimiento": "13/Dic/Dic/1998",
    "cedula": "67767340",
    "fecha_emision": "18/Mar/Mar/2025",
    "fecha_vencimiento": "18/Ene/Ene/2035",
    "sexo": "F",
    "nacionalidad": "VENEZOLANA",
    "lugar_nacimiento": "LA GUAIRA VEN",
    "codigo_verificacion": "13-12-98",
    "firma": "RoksGu",
    "fuente_firma": "White Sign (DemoVersion).otf",
    "mrz_linea1": "P<VENGUENTHERDOMENECH<<<<<<ROKSANA<<<<<<<<<<",
    "mrz_linea2": "1209105971VEN981213F0801012<<<<<<<<<<<<<<<4<",
    "edad": 26,
    "correo_original": "r0k54n4_gu3nth3r_13@hotmail.com",
    "imagen_usada": "/media/warcklian/DATA_500GB/CODE/SISTEMA_PASAPORTES_FINAL/DATA/Imagenes_Mujeres/massive_venezuelan_mujer_26_4042_20251002_103828.png",
    "nombre_archivo": "r0k54n4_gu3nth3r_13@hotmail.com.png",
    "pasaporte_visual": "/media/warcklian/DATA_500GB/CODE/SISTEMA_PASAPORTES_FINAL/OUTPUT/pasaportes_visuales/r0k54n4_gu3nth3r_13@hotmail.com.png",
    "estado": "generado"
  },
  {
    "ruta_foto": "/media/warcklian/DATA_500GB/CODE/SISTEMA_PASAPORTES_FINAL/DATA/Imagenes_Mujeres/massive_venezuelan_mujer_41_2581_20250930_171727.png",
    "numero_pasaporte_1": "163745180",
    "numero_pasaporte_2": "163745180",
    "numero_pasaporte": "163745180",
    "tipo": "P",
    "pais_emisor": "VEN",
    "nombre_completo": "ELLEN",
    "apellido_completo": "ANIYAH JEFFERSON",
    "fecha_nacimiento": "03/May/May/1984",
    "cedula": "98066659",
    "fecha_emision": "16/Ago/Ago/2024",
    "fecha_vencimiento": "16/Ene/Ene/2034",
    "sexo": "F",
    "nacionalidad": "VENEZOLANA",
    "lugar_nacimiento": "GUANARE VEN",
    "codigo_verificacion": "03-05-84",
    "firma": "E. Aniyah Jefferson",
    "fuente_firma": "White Sign (DemoVersion).otf",
    "mrz_linea1": "P<VENANIYAHJEFFERSON<<<<<<<ELLEN<<<<<<<<<<<<",
    "mrz_linea2": "1637451808VEN840503F9401014<<<<<<<<<<<<<<<2<",
    "edad": 41,
    "correo_original": "ell3n_4n1y4h_03@outlook.com",
    "imagen_usada": "/media/warcklian/DATA_500GB/CODE/SISTEMA_PASAPORTES_FINAL/DATA/Imagenes_Mujeres/massive_venezuelan_mujer_41_2581_20250930_171727.png",
    "nombre_archivo": "ell3n_4n1y4h_03@outlook.com.png",
    "pasaporte_visual": "/media/warcklian/DATA_500GB/CODE/SISTEMA_PASAPORTES_FINAL/OUTPUT/pasaportes_visuales/ell3n_4n1y4h_03@outlook.com.png",
    "estado": "generado"
  },
  {
    "ruta_foto": "/media/warcklian/DATA_500GB/CODE/SISTEMA_PASAPORTES_FINAL/DATA/Imagenes_Mujeres/massive_venezuelan_mujer_34_3590_20251002_103828.png",
    "numero_pasaporte_1": "131800338",
    "numero_pasaporte_2": "131800338",
    "numero_pasaporte": "131800338",
    "tipo": "P",
    "pais_emisor": "VEN",
    "nombre_completo": "ALTEA",
    "apellido_completo": "CACHO PACE",
    "fecha_nacimiento": "16/Oct/Oct/1990",
    "cedula": "20046876",
    "fecha_emision": "05/Sep/Sep/2024",
    "fecha_vencimiento": "05/Ene/Ene/2034",
    "sexo": "F",
    "nacionalidad": "VENEZOLANA",
    "lugar_nacimiento": "CORO VEN",
    "codigo_verificacion": "16-10-90",
    "firma": "A. Ca",
    "fuente_firma": "White Sign (DemoVersion).otf",
    "mrz_linea1": "P<VENCACHOPACE<<<<<<<<<<<<<ALTEA<<<<<<<<<<<<",
    "mrz_linea2": "1318003382VEN901016F0001016<<<<<<<<<<<<<<<6<",
    "edad": 34,
    "correo_original": "alt34_c4ch0_16@outlook.com",
    "imagen_usada": "/media/warcklian/DATA_500GB/CODE/SISTEMA_PASAPORTES_FINAL/DATA/Imagenes_Mujeres/massive_venezuelan_mujer_34_3590_20251002_103828.png",
    "nombre_archivo": "alt34_c4ch0_16@outlook.com.png",
    "pasaporte_visual": "/media/warcklian/DATA_500GB/CODE/SISTEMA_PASAPORTES_FINAL/OUTPUT/pasaportes_visuales/alt34_c4ch0_16@outlook.com.png",
    "estado": "generado"
  },
  {
    "ruta_foto": "/media/warcklian/DATA_500GB/CODE/SISTEMA_PASAPORTES_FINAL/DATA/Imagenes_Mujeres/massive_venezuelan_mujer_30_278_20250923_170855.png",
    "numero_pasaporte_1": "141987704",
    "numero_pasaporte_2": "141987704",
    "numero_pasaporte": "141987704",
    "tipo": "P",
    "pais_emisor": "VEN",
    "nombre_completo": "AMELIA",
    "apellido_completo": "SOFIA DRIS",
    "fecha_nacimiento": "21/May/May/1995",
    "cedula": "93248612",
    "fecha_emision": "22/Sep/Sep/2021",
    "fecha_vencimiento": "22/Ene/Ene/2031",
    "sexo": "F",
    "nacionalidad": "VENEZOLANA",
    "lugar_nacimiento": "MERIDA VEN",
    "codigo_verificacion": "21-05-95",
    "firma": "AmeSof",
    "fuente_firma": "White Sign (DemoVersion).otf",
    "mrz_linea1": "P<VENSOFIADRIS<<<<<<<<<<<<<AMELIA<<<<<<<<<<<",
    "mrz_linea2": "1419877048VEN950521F0501010<<<<<<<<<<<<<<<4<",
    "edad": 30,
    "correo_original": "am3l14_50f14_21@hotmail.com",
    "imagen_usada": "/media/warcklian/DATA_500GB/CODE/SISTEMA_PASAPORTES_FINAL/DATA/Imagenes_Mujeres/massive_venezuelan_mujer_30_278_20250923_170855.png",
    "nombre_archivo": "am3l14_50f14_21@hotmail.com.png",
    "pasaporte_visual": "/media/warcklian/DATA_500GB/CODE/SISTEMA_PASAPORTES_FINAL/OUTPUT/pasaportes_visuales/am3l14_50f14_21@hotmail.com.png",
    "estado": "generado"
  },
  {
    "ruta_foto": "/media/warcklian/DATA_500GB/CODE/SISTEMA_PASAPORTES_FINAL/DATA/Imagenes_Mujeres/massive_venezuelan_mujer_25_253_20250924_121313.png",
    "numero_pasaporte_1": "197619886",
    "numero_pasaporte_2": "197619886",
    "numero_pasaporte": "197619886",
    "tipo": "P",
    "pais_emisor": "VEN",
    "nombre_completo": "TADEA",
    "apellido_completo": "TORMES CALDERON",
    "fecha_nacimiento": "04/Nov/Nov/1999",
    "cedula": "79241024",
    "fecha_emision": "24/Mar/Mar/2022",
    "fecha_vencimiento": "24/Ene/Ene/2032",
    "sexo": "F",
    "nacionalidad": "VENEZOLANA",
    "lugar_nacimiento": "TRUJILLO VEN",
    "codigo_verificacion": "04-11-99",
    "firma": "Tad-T.",
    "fuente_firma": "White Sign (DemoVersion).otf",
    "mrz_linea1": "P<VENTORMESCALDERON<<<<<<<<TADEA<<<<<<<<<<<<",
    "mrz_linea2": "1976198868VEN991104F0901019<<<<<<<<<<<<<<<1<",
    "edad": 25,
    "correo_original": "t4d34_t0rm35_04@outlook.com",
    "imagen_usada": "/media/warcklian/DATA_500GB/CODE/SISTEMA_PASAPORTES_FINAL/DATA/Imagenes_Mujeres/massive_venezuelan_mujer_25_253_20250924_121313.png",
    "nombre_archivo": "t4d34_t0rm35_04@outlook.com.png",
    "pasaporte_visual": "/media/warcklian/DATA_500GB/CODE/SISTEMA_PASAPORTES_FINAL/OUTPUT/pasaportes_visuales/t4d34_t0rm35_04@outlook.com.png",
    "estado": "generado"
  },
  {
    "ruta_foto": "/media/warcklian/DATA_500GB/CODE/SISTEMA_PASAPORTES_FINAL/DATA/Imagenes_Mujeres/massive_venezuelan_mujer_32_275_20251002_103828.png",
    "numero_pasaporte_1": "127728432",
    "numero_pasaporte_2": "127728432",
    "numero_pasaporte": "127728432",
    "tipo": "P",
    "pais_emisor": "VEN",
    "nombre_completo": "CALLIOPE",
    "apellido_completo": "HAY ALONSO",
    "fecha_nacimiento": "18/Abr/Abr/1993",
    "cedula": "67216658",
    "fecha_emision": "07/Jul/Jul/2024",
    "fecha_vencimiento": "07/Ene/Ene/2034",
    "sexo": "F",
    "nacionalidad": "VENEZOLANA",
    "lugar_nacimiento": "SAN FELIPE VEN",
    "codigo_verificacion": "18-04-93",
    "firma": "Hay C.",
    "fuente_firma": "White Sign (DemoVersion).otf",
    "mrz_linea1": "P<VENHAYALONSO<<<<<<<<<<<<<CALLIOPE<<<<<<<<<",
    "mrz_linea2": "1277284322VEN930418F0301019<<<<<<<<<<<<<<<0<",
    "edad": 32,
    "correo_original": "c4ll10p3_h4y_18@hotmail.com",
    "imagen_usada": "/media/warcklian/DATA_500GB/CODE/SISTEMA_PASAPORTES_FINAL/DATA/Imagenes_Mujeres/massive_venezuelan_mujer_32_275_20251002_103828.png",
    "nombre_archivo": "c4ll10p3_h4y_18@hotmail.com.png",
    "pasaporte_visual": "/media/warcklian/DATA_500GB/CODE/SISTEMA_PASAPORTES_FINAL/OUTPUT/pasaportes_visuales/c4ll10p3_h4y_18@hotmail.com.png",
    "estado": "generado"
  },
  {
    "ruta_foto": "/media/warcklian/DATA_500GB/CODE/SISTEMA_PASAPORTES_FINAL/DATA/Imagenes_Mujeres/massive_venezuelan_mujer_28_2801_20251002_103828.png",
    "numero_pasaporte_1": "169979428",
    "numero_pasaporte_2": "169979428",
    "numero_pasaporte": "169979428",
    "tipo": "P",
    "pais_emisor": "VEN",
    "nombre_completo": "ELIZA",
    "apellido_completo": "ESSENCE COYNE",
    "fecha_nacimiento": "22/Jun/Jun/1997",
    "cedula": "53621479",
    "fecha_emision": "21/Sep/Sep/2021",
    "fecha_vencimiento": "21/Ene/Ene/2031",
    "sexo": "F",
    "nacionalidad": "VENEZOLANA",
    "lugar_nacimiento": "BARINAS VEN",
    "codigo_verificacion": "22-06-97",
    "firma": "EliEssence Coyne",
    "fuente_firma": "White Sign (DemoVersion).otf",
    "mrz_linea1": "P<VENESSENCECOYNE<<<<<<<<<<ELIZA<<<<<<<<<<<<",
    "mrz_linea2": "1699794280VEN970622F0701014<<<<<<<<<<<<<<<5<",
    "edad": 28,
    "correo_original": "el1z4_3553nc3_22@outlook.com",
    "imagen_usada": "/media/warcklian/DATA_500GB/CODE/SISTEMA_PASAPORTES_FINAL/DATA/Imagenes_Mujeres/massive_venezuelan_mujer_28_2801_20251002_103828.png",
    "nombre_archivo": "el1z4_3553nc3_22@outlook.com.png",
    "pasaporte_visual": "/media/warcklian/DATA_500GB/CODE/SISTEMA_PASAPORTES_FINAL/OUTPUT/pasaportes_visuales/el1z4_3553nc3_22@outlook.com.png",
    "estado": "generado"
  },
  {
    "ruta_foto": "/media/warcklian/DATA_500GB/CODE/SISTEMA_PASAPORTES_FINAL/DATA/Imagenes_Mujeres/massive_venezuelan_mujer_29_1608_20251002_103828.png",
    "numero_pasaporte_1": "172812250",
    "numero_pasaporte_2": "172812250",
    "numero_pasaporte": "172812250",
    "tipo": "P",
    "pais_emisor": "VEN",
    "nombre_completo": "SANDRA",
    "apellido_completo": "GUANUNA ABDELKADER",
    "fecha_nacimiento": "17/Sep/Sep/1970",
    "cedula": "22842803",
    "fecha_emision": "17/Mar/Mar/2023",
    "fecha_vencimiento": "17/Ene/Ene/2033",
    "sexo": "F",
    "nacionalidad": "VENEZOLANA",
    "lugar_nacimiento": "CORO VEN",
    "codigo_verificacion": "17-09-70",
    "firma": "Sand Guanuna Abdelkader",
    "fuente_firma": "White Sign (DemoVersion).otf",
    "mrz_linea1": "P<VENGUANUNAABDELKADER<<<<<SANDRA<<<<<<<<<<<",
    "mrz_linea2": "1728122501VEN700917F8001018<<<<<<<<<<<<<<<2<",
    "edad": 55,
    "correo_original": "s4ndr4_gu4nun4_17@outlook.com",
    "imagen_usada": "/media/warcklian/DATA_500GB/CODE/SISTEMA_PASAPORTES_FINAL/DATA/Imagenes_Mujeres/massive_venezuelan_mujer_29_1608_20251002_103828.png",
    "nombre_archivo": "s4ndr4_gu4nun4_17@outlook.com.png",
    "pasaporte_visual": "/media/warcklian/DATA_500GB/CODE/SISTEMA_PASAPORTES_FINAL/OUTPUT/pasaportes_visuales/s4ndr4_gu4nun4_17@outlook.com.png",
    "estado": "generado"
  },
  {
    "ruta_foto": "/media/warcklian/DATA_500GB/CODE/SISTEMA_PASAPORTES_FINAL/DATA/Imagenes_Mujeres/massive_venezuelan_mujer_28_1246_20250930_114813.png",
    "numero_pasaporte_1": "197548955",
    "numero_pasaporte_2": "197548955",
    "numero_pasaporte": "197548955",
    "tipo": "P",
    "pais_emisor": "VEN",
    "nombre_completo": "SHELLY",
    "apellido_completo": "ANIYAH PETERMAN",
    "fecha_nacimiento": "15/Feb/Feb/1997",
    "cedula": "37394259",
    "fecha_emision": "27/Jul/Jul/2023",
    "fecha_vencimiento": "27/Ene/Ene/2033",
    "sexo": "F",
    "nacionalidad": "VENEZOLANA",
    "lugar_nacimiento": "SAN FERNANDO DE APURE VEN",
    "codigo_verificacion": "15-02-97",
    "firma": "ShAn",
    "fuente_firma": "White Sign (DemoVersion).otf",
    "mrz_linea1": "P<VENANIYAHPETERMAN<<<<<<<<SHELLY<<<<<<<<<<<",
    "mrz_linea2": "1975489551VEN970215F0701017<<<<<<<<<<<<<<<5<",
    "edad": 28,
    "correo_original": "sh3lly_4n1y4h_15@hotmail.com",
    "imagen_usada": "/media/warcklian/DATA_500GB/CODE/SISTEMA_PASAPORTES_FINAL/DATA/Imagenes_Mujeres/massive_venezuelan_mujer_28_1246_20250930_114813.png",
    "nombre_archivo": "sh3lly_4n1y4h_15@hotmail.com.png",
    "pasaporte_visual": "/media/warcklian/DATA_500GB/CODE/SISTEMA_PASAPORTES_FINAL/OUTPUT/pasaportes_visuales/sh3lly_4n1y4h_15@hotmail.com.png",
    "estado": "generado"
  },
  {
    "ruta_foto": "/media/warcklian/DATA_500GB/CODE/SISTEMA_PASAPORTES_FINAL/DATA/Imagenes_Mujeres/massive_venezuelan_mujer_32_3759_20251002_103828.png",
    "numero_pasaporte_1": "186185911",
    "numero_pasaporte_2": "186185911",
    "numero_pasaporte": "186185911",
    "tipo": "P",
    "pais_emisor": "VEN",
    "nombre_completo": "VEGA",
    "apellido_completo": "SEGURA MORENO",
    "fecha_nacimiento": "26/Ene/Ene/1993",
    "cedula": "73371077",
    "fecha_emision": "13/Oct/Oct/2021",
    "fecha_vencimiento": "13/Ene/Ene/2031",
    "sexo": "F",
    "nacionalidad": "VENEZOLANA",
    "lugar_nacimiento": "MARACAY VEN",
    "codigo_verificacion": "26-01-93",
    "firma": "Vega Seg",
    "fuente_firma": "White Sign (DemoVersion).otf",
    "mrz_linea1": "P<VENSEGURAMORENO<<<<<<<<<<VEGA<<<<<<<<<<<<<",
    "mrz_linea2": "1861859113VEN930126F0301014<<<<<<<<<<<<<<<8<",
    "edad": 32,
    "correo_original": "v3g4_53gur4_26@outlook.com",
    "imagen_usada": "/media/warcklian/DATA_500GB/CODE/SISTEMA_PASAPORTES_FINAL/DATA/Imagenes_Mujeres/massive_venezuelan_mujer_32_3759_20251002_103828.png",
    "nombre_archivo": "v3g4_53gur4_26@outlook.com.png",
    "pasaporte_visual": "/media/warcklian/DATA_500GB/CODE/SISTEMA_PASAPORTES_FINAL/OUTPUT/pasaportes_visuales/v3g4_53gur4_26@outlook.com.png",
    "estado": "generado"
  }
]